spacyturk/__init__.py
spacyturk/__main__.py
spacyturk/api.py
spacyturk/pkg.py
spacyturk-0.1.0.dist-info/LICENSE
spacyturk-0.1.0.dist-info/METADATA
spacyturk-0.1.0.dist-info/WHEEL
spacyturk-0.1.0.dist-info/entry_points.txt
spacyturk-0.1.0.dist-info/top_level.txt
spacyturk-0.1.0.dist-info/RECORD
