Metadata-Version: 2.1
Name: spacyturk
Version: 0.1.0
Summary: spaCyTurk - trained spaCy models for Turkish
Author-email: "Bedii A. Aydoğan" <spacyturk@gmail.com>
License: MIT License
Project-URL: Homepage, https://github.com/spacyturk/spacyturk
Project-URL: Repository, https://github.com/spacyturk/spacyturk
Keywords: nlp,spacy,turkish,floret,fasttext
Classifier: License :: OSI Approved :: MIT License
Classifier: Programming Language :: Python
Classifier: Programming Language :: Python :: 3
Requires-Python: >=3.6
License-File: LICENSE
Requires-Dist: spacy (>=3.2.0)
Provides-Extra: build
Requires-Dist: build ; extra == 'build'
Requires-Dist: twine ; extra == 'build'
Provides-Extra: dev
Requires-Dist: pytest ; extra == 'dev'
